{
    "book": "Genesis",
    "chapter": 28,
    "quiz_structure": {
        "total_questions": 20,
        "sections": [
            {
                "name": "Factual Recall",
                "count": 10,
                "question_types": [
                    "key_facts",
                    "details",
                    "concepts",
                    "terms",
                    "events",
                    "characters",
                    "teachings",
                    "settings",
                    "sequence"
                ],
                "questions": [
                    {
                        "question": {
                            "text": "Who did Isaac send to Paddan-aram to find a wife?",
                            "options": [
                                "Jacob",
                                "Esau",
                                "Isaac",
                                "Abraham"
                            ],
                            "correct_answer": 0
                        }
                    },
                    {
                        "question": {
                            "text": "At which place did Jacob have a dream about a ladder reaching to heaven?",
                            "options": [
                                "Bethel",
                                "Beersheba",
                                "Haran",
                                "Hebron"
                            ],
                            "correct_answer": 0
                        }
                    },
                    {
                        "question": {
                            "text": "In Jacob's dream, who were ascending and descending on the ladder?",
                            "options": [
                                "Angels",
                                "Animals",
                                "People",
                                "God"
                            ],
                            "correct_answer": 0
                        }
                    },
                    {
                        "question": {
                            "text": "What did God promise Jacob in the dream?",
                            "options": [
                                "To give him the land",
                                "To make his descendants numerous",
                                "To be with him wherever he goes",
                                "All of the above"
                            ],
                            "correct_answer": 3
                        }
                    },
                    {
                        "question": {
                            "text": "What did Jacob use as a pillow when he had the dream?",
                            "options": [
                                "A rock",
                                "A tree root",
                                "A pile of leaves",
                                "A backpack"
                            ],
                            "correct_answer": 0
                        }
                    },
                    {
                        "question": {
                            "text": "What did Jacob name the place after his dream?",
                            "options": [
                                "Bethel",
                                "House of God",
                                "Gate of Heaven",
                                "Both A and B"
                            ],
                            "correct_answer": 3
                        }
                    },
                    {
                        "question": {
                            "text": "What vow did Jacob make after his dream?",
                            "options": [
                                "To tithe a tenth of his earnings to God",
                                "To always worship at Bethel",
                                "To serve God faithfully",
                                "To never leave the promised land"
                            ],
                            "correct_answer": 2
                        }
                    },
                    {
                        "question": {
                            "text": "Who did Jacob meet in Paddan-aram?",
                            "options": [
                                "Laban",
                                "Rachel",
                                "Leah",
                                "All of the above"
                            ],
                            "correct_answer": 3
                        }
                    },
                    {
                        "question": {
                            "text": "How many years did Jacob agree to work for Laban in order to marry Rachel?",
                            "options": [
                                "5 years",
                                "7 years",
                                "10 years",
                                "14 years"
                            ],
                            "correct_answer": 1
                        }
                    },
                    {
                        "question": {
                            "text": "Why did Laban trick Jacob into marrying Leah first?",
                            "options": [
                                "Leah was older",
                                "Laban wanted more money",
                                "Rachel was not ready for marriage",
                                "It was the custom of the land"
                            ],
                            "correct_answer": 0
                        }
                    }
                ]
            },
            {
                "name": "Comprehension and Analysis",
                "count": 6,
                "question_types": [
                    "main_ideas",
                    "concept_relationships",
                    "interpretation",
                    "author_intent",
                    "compare_contrast",
                    "significance"
                ],
                "questions": [
                    {
                        "question": {
                            "text": "What is the significance of Jacob's dream in relation to God's covenant?",
                            "options": [
                                "It reaffirms God's promise to Abraham",
                                "It shows God's faithfulness despite human weaknesses",
                                "It foreshadows the future of Jacob's descendants",
                                "All of the above"
                            ],
                            "correct_answer": 3
                        }
                    },
                    {
                        "question": {
                            "text": "How does Jacob's character develop throughout this chapter?",
                            "options": {
                                "type": "input"
                            },
                            "correct_answer": "Jacob matures from a deceiver to a faithful servant of God, recognizing God's presence and making a vow of commitment."
                        }
                    },
                    {
                        "question": {
                            "text": "What can we learn about God's nature from this chapter?",
                            "options": [
                                "God is omnipresent",
                                "God keeps His promises",
                                "God guides and protects His chosen ones",
                                "All of the above"
                            ],
                            "correct_answer": 3
                        }
                    },
                    {
                        "question": {
                            "text": "How does the author use repetition to emphasize key themes in this chapter?",
                            "options": [
                                "Repeating God's promises",
                                "Repeating Jacob's vow",
                                "Repeating descriptions of Bethel",
                                "Repeating the names of characters"
                            ],
                            "correct_answer": 0
                        }
                    },
                    {
                        "question": {
                            "text": "Contrast Jacob's experience at Bethel with his later experience in Paddan-aram.",
                            "options": {
                                "type": "input"
                            },
                            "correct_answer": "At Bethel, Jacob directly encounters God and experiences His presence. In Paddan-aram, Jacob faces human challenges and deception, but God remains faithful."
                        }
                    },
                    {
                        "question": {
                            "text": "What is the significance of Jacob's vow in the context of his journey?",
                            "options": [
                                "It marks his personal commitment to God",
                                "It sets the stage for his future role in God's plan",
                                "It highlights the conditional nature of God's blessings",
                                "All of the above"
                            ],
                            "correct_answer": 3
                        }
                    }
                ]
            },
            {
                "name": "Application",
                "count": 2,
                "question_types": [
                    "new_situations",
                    "daily_life"
                ],
                "questions": [
                    {
                        "question": {
                            "text": "How can we apply the lessons from Jacob's dream to our own spiritual lives?",
                            "options": {
                                "type": "input"
                            },
                            "correct_answer": "Like Jacob, we should recognize God's presence in our lives, trust in His promises, and commit to serving Him faithfully wherever we are."
                        }
                    },
                    {
                        "question": {
                            "text": "In what ways can we live out Jacob's vow in our daily lives?",
                            "options": {
                                "type": "input"
                            },
                            "correct_answer": "We can live out Jacob's vow by acknowledging God's provision, dedicating ourselves to His service, and faithfully giving back to Him through tithes and offerings."
                        }
                    }
                ]
            },
            {
                "name": "Reflection",
                "count": 2,
                "question_types": [
                    "main_takeaway",
                    "biblical_connections"
                ],
                "questions": [
                    {
                        "question": {
                            "text": "What is your main takeaway from Genesis 28?",
                            "options": {
                                "type": "input"
                            },
                            "correct_answer": "My main takeaway is that God's promises and faithfulness are not dependent on human merit, but rather on His grace and sovereignty. Jacob, despite his flaws, was chosen and blessed by God."
                        }
                    },
                    {
                        "question": {
                            "text": "How does Genesis 28 connect to other parts of the Bible?",
                            "options": {
                                "type": "input"
                            },
                            "correct_answer": "Genesis 28 connects to other parts of the Bible by foreshadowing the future of Israel (Jacob's descendants), by paralleling other divine encounters (e.g., Moses at the burning bush), and by emphasizing God's covenant faithfulness (e.g., in the New Testament through Christ)."
                        }
                    }
                ]
            }
        ]
    },
    "key_themes": [
        "God's faithfulness",
        "Jacob's transformation",
        "Covenant promises"
    ],
    "key_verses": [
        {
            "reference": "Genesis 28:15"
        },
        {
            "reference": "Genesis 28:20-21"
        }
    ],
    "characters": [
        {
            "name": "Jacob",
            "role": "Patriarch, recipient of God's promises"
        },
        {
            "name": "Isaac",
            "role": "Jacob's father, sender of Jacob to Paddan-aram"
        },
        {
            "name": "Laban",
            "role": "Jacob's uncle and father-in-law"
        },
        {
            "name": "Rachel",
            "role": "Jacob's cousin and wife-to-be"
        },
        {
            "name": "Leah",
            "role": "Jacob's cousin and first wife"
        }
    ],
    "events": [
        {
            "description": "Jacob's dream at Bethel",
            "location": "Bethel (Luz)"
        },
        {
            "description": "Jacob's arrival in Paddan-aram",
            "location": "Paddan-aram (Haran)"
        }
    ],
    "concepts": [
        "Covenant",
        "Divine encounter",
        "Promise",
        "Faithfulness",
        "Transformation"
    ],
    "cross_references": {
        "Old Testament": [
            {
                "reference": "Genesis 12:1-3",
                "description": "God's initial covenant promise to Abraham"
            },
            {
                "reference": "Genesis 35:1-15",
                "description": "Jacob's return to Bethel and renaming"
            }
        ],
        "New Testament": [
            {
                "reference": "John 1:51",
                "description": "Jesus refers to himself as the ladder between heaven and earth"
            },
            {
                "reference": "Hebrews 11:9-10",
                "description": "Jacob's faith in God's promises"
            }
        ]
    }
}