{
    "book": "Genesis",
    "chapter": 23,
    "quiz_structure": {
        "total_questions": 20,
        "sections": [
            {
                "name": "Factual Recall",
                "count": 10,
                "question_types": [
                    "key_facts",
                    "details",
                    "concepts",
                    "terms",
                    "events",
                    "characters",
                    "teachings",
                    "settings",
                    "sequence"
                ],
                "questions": [
                    {
                        "question": {
                            "text": "Who bought the cave of Machpelah from Ephron the Hittite in Genesis 23:16-18?",
                            "options": [
                                "Abraham",
                                "Isaac",
                                "Ephron the Hittite",
                                "Lot"
                            ],
                            "correct_answer": 0
                        }
                    },
                    {
                        "question": {
                            "text": "What was the price Abraham paid for the cave of Machpelah?",
                            "options": [
                                "400 shekels of silver",
                                "100 shekels of silver",
                                "200 shekels of silver",
                                "300 shekels of silver"
                            ],
                            "correct_answer": 0
                        }
                    },
                    {
                        "question": {
                            "text": "What was the name of Abraham's wife who died in Genesis 23:2?",
                            "options": [
                                "Sarah",
                                "Rebekah",
                                "Rachel",
                                "Leah"
                            ],
                            "correct_answer": 0
                        }
                    },
                    {
                        "question": {
                            "text": "Where did Abraham go to buy a burial plot for his wife in Genesis 23:2?",
                            "options": [
                                "Hebron",
                                "Shechem",
                                "Bethlehem",
                                "Mamre"
                            ],
                            "correct_answer": 0
                        }
                    },
                    {
                        "question": {
                            "text": "Who was the Hittite who sold the cave of Machpelah to Abraham in Genesis 23:16-18?",
                            "options": [
                                "Ephron the Hittite",
                                "Abraham",
                                "Isaac",
                                "Lot"
                            ],
                            "correct_answer": 0
                        }
                    },
                    {
                        "question": {
                            "text": "What was the cave of Machpelah used for in Genesis 23:17?",
                            "options": [
                                "A burial site",
                                "A place of worship",
                                "A field for agriculture",
                                "A location for trade"
                            ],
                            "correct_answer": 0
                        }
                    },
                    {
                        "question": {
                            "text": "Who helped Abraham in his negotiations with Ephron the Hittite in Genesis 23:2?",
                            "options": [
                                "Abimelech",
                                "Phicol",
                                "Ephron the Hittite",
                                "Lot"
                            ],
                            "correct_answer": 0
                        }
                    },
                    {
                        "question": {
                            "text": "How old was Isaac when his mother, Sarah, died in Genesis 23:2?",
                            "options": [
                                "37 years",
                                "27 years",
                                "37 years old",
                                "100 years"
                            ],
                            "correct_answer": 0
                        }
                    },
                    {
                        "question": {
                            "text": "Who helped Abraham in purchasing the cave of Machpelah in Genesis 23:18?",
                            "options": [
                                "Abimelech",
                                "Phicol",
                                "Ephron the Hittite",
                                "Lot"
                            ],
                            "correct_answer": 0
                        }
                    },
                    {
                        "question": {
                            "text": "What was the reason for Abraham's urgency in purchasing a burial plot in Genesis 23:2?",
                            "options": [
                                "He wanted to bury his wife quickly",
                                "He wanted to show respect to his wife's memory",
                                "He wanted to appease the Hittites",
                                "He wanted to fulfill a promise to God"
                            ],
                            "correct_answer": 1
                        }
                    }
                ]
            },
            {
                "name": "Comprehension and Analysis",
                "count": 6,
                "question_types": [
                    "main_ideas",
                    "concept_relationships",
                    "interpretation",
                    "author_intent",
                    "compare_contrast",
                    "significance"
                ],
                "questions": [
                    {
                        "question": {
                            "text": "What is the main idea of Genesis 23:1-20?",
                            "options": [
                                "Abraham's journey to the land of the Hittites",
                                "Abraham's purchase of the cave of Machpelah",
                                "The death of Abraham's wife, Sarah",
                                "The burial of Abraham's wife, Sarah"
                            ],
                            "correct_answer": 3
                        }
                    },
                    {
                        "question": {
                            "text": "How does the purchase of the cave of Machpelah relate to the larger story of Genesis?",
                            "options": [
                                "It is a minor detail in the story of Abraham's journey",
                                "It is a key event in the story of the patriarchs",
                                "It is a symbol of Abraham's faith in God",
                                "It is a demonstration of Abraham's wealth and power"
                            ],
                            "correct_answer": 2
                        }
                    },
                    {
                        "question": {
                            "text": "What does the fact that Ephron the Hittite sold the cave of Machpelah to Abraham for a high price suggest about the Hittites' views on Abraham?",
                            "options": [
                                "They saw Abraham as a worthy adversary",
                                "They saw Abraham as a powerful and influential leader",
                                "They saw Abraham as a wealthy and respected member of their community",
                                "They saw Abraham as a threat to their way of life"
                            ],
                            "correct_answer": 2
                        }
                    },
                    {
                        "question": {
                            "text": "How does the story of the purchase of the cave of Machpelah relate to the broader themes of Genesis?",
                            "options": [
                                "It emphasizes the importance of family and community",
                                "It highlights the challenges and struggles of the patriarchs",
                                "It demonstrates the importance of faith and trust in God",
                                "It shows the impact of human sin on relationships"
                            ],
                            "correct_answer": 3
                        }
                    },
                    {
                        "question": {
                            "text": "What does the fact that Abraham was willing to pay a high price for the cave of Machpelah suggest about his character?",
                            "options": [
                                "He was a stingy and frugal man",
                                "He was a generous and willing to spend money to achieve his goals",
                                "He was a foolish and impulsive man",
                                "He was a humble and unassuming man"
                            ],
                            "correct_answer": 1
                        }
                    },
                    {
                        "question": {
                            "text": "How does the story of the purchase of the cave of Machpelah reflect the character of God?",
                            "options": [
                                "It shows God as a harsh and unforgiving judge",
                                "It highlights God's love and compassion for his people",
                                "It demonstrates God's desire for justice and fairness",
                                "It shows God's willingness to work with human beings to achieve his goals"
                            ],
                            "correct_answer": 2
                        }
                    }
                ]
            },
            {
                "name": "Application",
                "count": 2,
                "question_types": [
                    "new_situations",
                    "daily_life"
                ],
                "questions": [
                    {
                        "question": {
                            "text": "How would you handle a situation where you need to purchase a property, but the owner is not willing to sell it to you?",
                            "options": {
                                "type": "input"
                            },
                            "correct_answer": null
                        }
                    },
                    {
                        "question": {
                            "text": "How can you apply the principles of Genesis 23:1-20 to your own life, such as being willing to negotiate and compromise to achieve your goals?",
                            "options": {
                                "type": "input"
                            },
                            "correct_answer": null
                        }
                    }
                ]
            },
            {
                "name": "Reflection",
                "count": 2,
                "question_types": [
                    "main_takeaway",
                    "biblical_connections"
                ],
                "questions": [
                    {
                        "question": {
                            "text": "What is the main takeaway from the story of the purchase of the cave of Machpelah in Genesis 23:1-20?",
                            "options": {
                                "type": "input"
                            },
                            "correct_answer": null
                        }
                    },
                    {
                        "question": {
                            "text": "How does the story of the purchase of the cave of Machpelah connect to other stories in the Bible, such as the story of the Israelites' conquest of the land?",
                            "options": {
                                "type": "input"
                            },
                            "correct_answer": null
                        }
                    }
                ]
            }
        ]
    },
    "key_themes": [
        "Faith",
        "Family",
        "Community",
        "Burial",
        "Property",
        "Negotiation",
        "Compromise"
    ],
    "key_verses": [
        {
            "reference": "Genesis 23:4"
        }
    ],
    "characters": [
        {
            "name": "Abraham",
            "role": "Protagonist"
        },
        {
            "name": "Ephron the Hittite",
            "role": "Antagonist"
        },
        {
            "name": "Sarah",
            "role": "Supporting character"
        },
        {
            "name": "Isaac",
            "role": "Supporting character"
        }
    ],
    "events": [
        {
            "description": "Abraham's purchase of the cave of Machpelah",
            "location": "Hebron"
        }
    ],
    "concepts": [
        "Faith",
        "Family",
        "Community",
        "Burial",
        "Property",
        "Negotiation",
        "Compromise"
    ],
    "cross_references": {
        "Old Testament": [
            {
                "reference": "Genesis 23:2",
                "description": "Abraham's purchase of the cave of Machpelah"
            }
        ],
        "New Testament": [
            {
                "reference": "Hebrews 11:13",
                "description": "Abraham's faith in God"
            }
        ]
    }
}